[
  { "name": "John Smith", "email": "john.smith@email.com", "phone": "9876543210", "bloodGroup": "A+", "location": "Hyderabad" },
  { "name": "Maria Garcia", "email": "maria.garcia@email.com", "phone": "9876543211", "bloodGroup": "A-", "location": "Guntur" },
  { "name": "David Johnson", "email": "david.johnson@email.com", "phone": "9876543212", "bloodGroup": "B+", "location": "Vijayawada" },
  { "name": "Sarah Williams", "email": "sarah.williams@email.com", "phone": "9876543213", "bloodGroup": "B-", "location": "Vizag" },
  { "name": "Michael Brown", "email": "michael.brown@email.com", "phone": "9876543214", "bloodGroup": "O+", "location": "Banglore" },
  { "name": "Emily Davis", "email": "emily.davis@email.com", "phone": "9876543215", "bloodGroup": "O-", "location": "Mumbai" },
  { "name": "Robert Miller", "email": "robert.miller@email.com", "phone": "9876543216", "bloodGroup": "AB+", "location": "Kadapa" },
  { "name": "Jennifer Wilson", "email": "jennifer.wilson@email.com", "phone": "9876543217", "bloodGroup": "AB-", "location": "Bhimavaram" },
  { "name": "James Anderson", "email": "james.anderson@email.com", "phone": "9876543218", "bloodGroup": "A+", "location": "Pune" },
  { "name": "Lisa Thomas", "email": "lisa.thomas@email.com", "phone": "9876543219", "bloodGroup": "O+", "location": "Kolkata" },
  { "name": "Christopher Lee", "email": "christopher.lee@email.com", "phone": "9876543220", "bloodGroup": "A+", "location": "Delhi" },
  { "name": "Jessica Martinez", "email": "jessica.martinez@email.com", "phone": "9876543221", "bloodGroup": "A-", "location": "Chennai" },
  { "name": "Daniel Robinson", "email": "daniel.robinson@email.com", "phone": "9876543222", "bloodGroup": "B+", "location": "Kolkata" },
  { "name": "Amanda Clark", "email": "amanda.clark@email.com", "phone": "9876543223", "bloodGroup": "B-", "location": "Jaipur" },
  { "name": "Matthew Rodriguez", "email": "matthew.rodriguez@email.com", "phone": "9876543224", "bloodGroup": "O+", "location": "Hyderabad" },
  { "name": "Stephanie Lewis", "email": "stephanie.lewis@email.com", "phone": "9876543225", "bloodGroup": "O-", "location": "Pune" },
  { "name": "Andrew Walker", "email": "andrew.walker@email.com", "phone": "9876543226", "bloodGroup": "AB+", "location": "Mumbai" },
  { "name": "Nicole Hall", "email": "nicole.hall@email.com", "phone": "9876543227", "bloodGroup": "AB-", "location": "Delhi" },
  { "name": "Joshua Allen", "email": "joshua.allen@email.com", "phone": "9876543228", "bloodGroup": "A+", "location": "Chennai" },
  { "name": "Rachel Young", "email": "rachel.young@email.com", "phone": "9876543229", "bloodGroup": "O+", "location": "Banglore" },
  { "name": "Ryan King", "email": "ryan.king@email.com", "phone": "9876543230", "bloodGroup": "A+", "location": "Vizag" },
  { "name": "Michelle Wright", "email": "michelle.wright@email.com", "phone": "9876543231", "bloodGroup": "A-", "location": "Vijayawada" },
  { "name": "Kevin Scott", "email": "kevin.scott@email.com", "phone": "9876543232", "bloodGroup": "B+", "location": "Guntur" },
  { "name": "Laura Green", "email": "laura.green@email.com", "phone": "9876543233", "bloodGroup": "B-", "location": "Kadapa" },
  { "name": "Brandon Baker", "email": "brandon.baker@email.com", "phone": "9876543234", "bloodGroup": "O+", "location": "Mumbai" },
  { "name": "Samantha Adams", "email": "samantha.adams@email.com", "phone": "9876543235", "bloodGroup": "O-", "location": "Delhi" },
  { "name": "Justin Nelson", "email": "justin.nelson@email.com", "phone": "9876543236", "bloodGroup": "AB+", "location": "Pune" },
  { "name": "Heather Carter", "email": "heather.carter@email.com", "phone": "9876543237", "bloodGroup": "AB-", "location": "Chennai" },
  { "name": "Tyler Mitchell", "email": "tyler.mitchell@email.com", "phone": "9876543238", "bloodGroup": "A+", "location": "Banglore" },
  { "name": "Megan Perez", "email": "megan.perez@email.com", "phone": "9876543239", "bloodGroup": "O+", "location": "Kolkata" },
  { "name": "Jacob Roberts", "email": "jacob.roberts@email.com", "phone": "9876543240", "bloodGroup": "A+", "location": "Hyderabad" },
  { "name": "Brittany Turner", "email": "brittany.turner@email.com", "phone": "9876543241", "bloodGroup": "A-", "location": "Vizag" },
  { "name": "Austin Phillips", "email": "austin.phillips@email.com", "phone": "9876543242", "bloodGroup": "B+", "location": "Pune" },
  { "name": "Kimberly Campbell", "email": "kimberly.campbell@email.com", "phone": "9876543243", "bloodGroup": "B-", "location": "Mumbai" },
  { "name": "Jordan Parker", "email": "jordan.parker@email.com", "phone": "9876543244", "bloodGroup": "O+", "location": "Delhi" },
  { "name": "Whitney Evans", "email": "whitney.evans@email.com", "phone": "9876543245", "bloodGroup": "O-", "location": "Chennai" },
  { "name": "Corey Edwards", "email": "corey.edwards@email.com", "phone": "9876543246", "bloodGroup": "AB+", "location": "Banglore" },
  { "name": "Candice Collins", "email": "candice.collins@email.com", "phone": "9876543247", "bloodGroup": "AB-", "location": "Jaipur" },
  { "name": "Jeremy Stewart", "email": "jeremy.stewart@email.com", "phone": "9876543248", "bloodGroup": "A+", "location": "Kolkata" },
  { "name": "Amber Sanchez", "email": "amber.sanchez@email.com", "phone": "9876543249", "bloodGroup": "O+", "location": "Vijayawada" },
  { "name": "Derek Morris", "email": "derek.morris@email.com", "phone": "9876543250", "bloodGroup": "A+", "location": "Guntur" },
  { "name": "Kelli Rogers", "email": "kelli.rogers@email.com", "phone": "9876543251", "bloodGroup": "A-", "location": "Bhimavaram" },
  { "name": "Gregory Reed", "email": "gregory.reed@email.com", "phone": "9876543252", "bloodGroup": "B+", "location": "Kadapa" },
  { "name": "Danielle Cook", "email": "danielle.cook@email.com", "phone": "9876543253", "bloodGroup": "B-", "location": "Hyderabad" },
  { "name": "Marcus Morgan", "email": "marcus.morgan@email.com", "phone": "9876543254", "bloodGroup": "O+", "location": "Pune" },
  { "name": "Jenna Bell", "email": "jenna.bell@email.com", "phone": "9876543255", "bloodGroup": "O-", "location": "Banglore" },
  { "name": "Blake Murphy", "email": "blake.murphy@email.com", "phone": "9876543256", "bloodGroup": "AB+", "location": "Mumbai" },
  { "name": "Tara Bailey", "email": "tara.bailey@email.com", "phone": "9876543257", "bloodGroup": "AB-", "location": "Delhi" },
  { "name": "Brett Rivera", "email": "brett.rivera@email.com", "phone": "9876543258", "bloodGroup": "A+", "location": "Chennai" },
  { "name": "Katelyn Cooper", "email": "katelyn.cooper@email.com", "phone": "9876543259", "bloodGroup": "O+", "location": "Vizag" }
]

